pg_dbconnect/DBConnect.py
pg_dbconnect/__init__.py
pg_dbconnect-2.5.2.dist-info/licenses/LICENCE
pg_dbconnect-2.5.2.dist-info/METADATA
pg_dbconnect-2.5.2.dist-info/WHEEL
pg_dbconnect-2.5.2.dist-info/top_level.txt
pg_dbconnect-2.5.2.dist-info/RECORD
