Metadata-Version: 2.4
Name: pg_dbconnect
Version: 2.5.2
Summary: A utility for PostgreSQL/PostGIS integration and data handling
Author-email: JVL <jeevrlendio@gmail.com>
Classifier: Programming Language :: Python :: 3
Classifier: Operating System :: OS Independent
Requires-Python: >=3.8
License-File: LICENCE
Requires-Dist: pandas
Requires-Dist: geopandas
Requires-Dist: fiona
Requires-Dist: psycopg2
Requires-Dist: sqlalchemy
Requires-Dist: openpyxl
Dynamic: license-file
